{
  "category": "enigmatic_legacy:equipment",
  "icon": "enigmatic_legacy:etherium_axe",
  "name": "以太斧",
  "pages": [
    {
      "type": "patchouli:spotlight",
      "item": "enigmatic_legacy:etherium_axe",
      "link_recipe": true,
      "text": "既是工具，也是武器的以太战斧。$(br2)它适合伐木，也可以作为可靠的近战装备。",
      "title": "以太斧"
    },
    {
      "type": "patchouli:crafting",
      "recipe": "enigmatic_legacy:etherium_axe",
      "text": "合成配方 / Crafting Recipe",
      "title": " "
    }
  ],
  "read_by_default": true,
  "secret": false,
  "sortnum": 50
}