{
  "category": "enigmatic_legacy:relics",
  "icon": "enigmatic_legacy:the_acknowledgment",
  "name": "启示之证",
  "pages": [
    {
      "type": "patchouli:spotlight",
      "item": "enigmatic_legacy:the_acknowledgment",
      "link_recipe": true,
      "text": "启示之证既是神秘手册，也是一件古老遗物。$(br2)右键使用它可以打开这本手册，查看遗物、术石、卷轴、诅咒与隐藏知识。",
      "title": "启示之证"
    },
    {
      "type": "patchouli:text",
      "text": "启示之证不会被消耗，也不需要装备到饰品栏。$(br2)手持它并右键即可阅读当前记录的知识。",
      "title": "作为手册"
    },
    {
      "type": "patchouli:text",
      "text": "启示之证也可以被当作武器挥动。$(br2)它能造成少量伤害，使被击中的敌人燃烧，并且可以附魔。",
      "title": "作为武器"
    },
    {
      "type": "patchouli:text",
      "text": "当持有者承受七咒之戒时，启示之证会削弱部分诅咒痛苦。$(br2)它不能完全移除诅咒，但能让生存稍微宽容一些。",
      "title": "诅咒共鸣"
    },
    {
      "type": "patchouli:crafting",
      "recipe": "enigmatic_legacy:the_acknowledgment",
      "text": "合成启示之证后，右键即可打开这本手册。",
      "title": " "
    }
  ],
  "read_by_default": true,
  "secret": false,
  "sortnum": 0
}